pypitzer/__init__.py
pypitzer/MCWEP/68_uncert_confidence_interval.py
pypitzer/MCWEP/95_uncert_confidence_interval.py
pypitzer/MCWEP/__init__.py
pypitzer/MCWEP/meta.py
pypitzer/MCWEP/methods.py
pypitzer/MCWEP/models.py
pypitzer/MCWEP/models_low_t.py
pypitzer/MCWEP/newton_raphson.py
pypitzer/MCWEP/statistic_analysis.py
pypitzer/Pitzer/__init__.py
pypitzer/Pitzer/methods.py
pypitzer/Pitzer/model2.py
pypitzer/Pitzer/models.py
pypitzer/database/__init__.py
pypitzer/database/create_sqlite.py
pypitzer/database/db_query.py
pypitzer/database/insert_binary.py
pypitzer/database/insert_reaction.py
pypitzer/database/insert_ternary.py
pypitzer/database/lassin_binary.py
pypitzer/database/lassin_chemical_potential.py
pypitzer/database/lassin_chemical_potentials.py
pypitzer/database/lassin_ternary.py
pypitzer/database/pypitzer.sqlite
pypitzer/examples/quantification/cotectic_calculate.py
pypitzer/examples/quantification/fi_quantification.py
pypitzer/examples/uncertainty/MCWEP/test.py
pypitzer/examples/uncertainty/MCWEP/test2.py
pypitzer/examples/uncertainty/MCWEP/test3.py
pypitzer/public/__init__.py
pypitzer/public/icemelting.py
pypitzer/public/j_x.py
pypitzer/public/low_level.py
pypitzer/uncertainty/__init__.py
pypitzer/uncertainty/execute.py
pypitzer/uncertainty/methods.py
pypitzer/uncertainty/models.py
pypitzer-1.1.5.dist-info/METADATA
pypitzer-1.1.5.dist-info/WHEEL
pypitzer-1.1.5.dist-info/licenses/LICENSE
pypitzer-1.1.5.dist-info/RECORD
