Metadata-Version: 2.4
Name: pypitzer
Version: 1.1.5
Summary: A library for thermodynamic modeling with the Pitzer model and its application in quantification of fluid inclusion data.
Project-URL: Homepage, https://github.com/pypitzer/pypitzer
Project-URL: Bug Tracker, https://github.com/pypitzer/pypitzer/issues
Author-email: Yiping Liu <yiping.liu@rwth-aachen.de>
License: MIT
License-File: LICENSE
Keywords: fluid-inclusions,geochemistry,pitzer,thermodynamics
Classifier: License :: OSI Approved :: MIT License
Classifier: Operating System :: OS Independent
Classifier: Programming Language :: Python :: 3
Requires-Python: >=3.7
